[
   {
   "gombal": "Kamu tau gak? Kenapa kalau aku menghafal lihatnya ke atas? soalnya kalau merem langsung kebayang wajahmu.",
   "gombal": "Orang kurus itu setia, makan aja tidak pernah nambah apalagi pasangan.",
   "gombal": "Kamu tu kayak warteg, sederhana namun berkualitas.",
   "gombal": "Aku gak sedih kok kalo besok hari senin, aku sedihnya kalau gak ketemu kamu.",
   "gombal": "Cintaku kepadamu itu bagaikan metabolisme, yang gak akan berhenti sampai mati.",
   "gombal": "Kamu tau gak apa persamaannya kamu sama AC? Sama-sama bikin aku sejuk.",
   "gombal": "Aku hanya ingin hidup cukup. Cukup lihat senyummu setiap hari.",
   "gombal": "Aku rela ikut lomba lari keliling dunia, asalkan engkau yang menjadi garis finisnya.",
   "gombal": "Kalau orang kebutuhan primernya ada tiga yaitu sandang pangan dan papan, tapi kalau aku : kamu, kamu, kamu.",
   "gombal": "Cita-citaku dulu pengen jadi dokter, tapi setelah mengenalmu, berubah jadi ingin membahagiakanmu.",
   "gombal": "Enak ya jadi kamu, kalau mau liat bidadari, tinggal liat di kaca.",
   "gombal": "Jika kamu tanya berapa kali kamu datang ke pikiranku, jujur saja, cuma sekali. Habisnya, gak pergi-pergi sih!",
   "gombal": "Jangan GR deh. Aku kangen kamu sedikit aja kok. Sedikit berlebihan maksudnya.",
   "gombal": "Tanggal merah sekalipun aku tidak libur untuk memikirkan kamu.",
   "gombal": "Cintaku padamu bagai diare. Tak bisa kutahan, terus keluar begitu saja.",
   "gombal": "Aku ga lulus ulangan umum sayang, gara-gara di bagian essay-nya aku tulis surat cinta buat kamu.",
   "gombal": "Tahu gak kenapa kita cuma bisa lihat pelangi setengah lingkaran? Sebab setengahnya lagi ada di mata kamu.",
   "gombal": "Kalo kamu lagi di AS, Patung Liberty ga akan bawa obor tapi bakal bawa BUNGA!",
   "gombal": "Aku rela jadi abang nasi goreng asalkan setiap malam aku bisa lewat depan rumah kamu.",
   "gombal": "Aku rela dipenjara seumur hidup asalkan pelanggarannya karena mencintaimu.",
   "gombal": "Kamu tau gak? Lukisan itukan makin lama makin antik, kalo kamu makin lama makin cantik"
   }
]